minigram/__init__.py
minigram/aiohttp.py
minigram/fastapi.py
minigram/main.py
minigram/py.typed
minigram/request.py
minigram/starlette.py
minigram_py-0.5.0.dist-info/METADATA
minigram_py-0.5.0.dist-info/WHEEL
minigram_py-0.5.0.dist-info/entry_points.txt
minigram_py-0.5.0.dist-info/licenses/LICENSE
minigram_py-0.5.0.dist-info/RECORD
