Metadata-Version: 2.1
Name: minigram-py
Version: 0.5.0
Summary: minimalistic telegram bot framework that can be used in AWS Lambda or anywhere
Author-Email: Grigory Bakunov <bobuk@rubedo.cloud>
License: MIT
Requires-Python: >=3.12
Provides-Extra: starlette
Requires-Dist: starlette>=0.37.2; extra == "starlette"
Provides-Extra: aiohttp
Requires-Dist: aiohttp>=3.9.3; extra == "aiohttp"
Provides-Extra: httpx
Requires-Dist: httpx>=0.18.0; extra == "httpx"
Provides-Extra: fastapi
Requires-Dist: fastapi>=0.73.0; extra == "fastapi"
